misu/SIprefixes.py
misu/__init__.py
misu/addmodule.py
misu/engine.cp36-win_amd64.pyd
misu/make_README.py
misu/misulib.py
misu/profiler_support.py
misu/unitmachine.py
misu-1.0.6.dist-info/LICENCE.txt
misu-1.0.6.dist-info/METADATA
misu-1.0.6.dist-info/WHEEL
misu-1.0.6.dist-info/top_level.txt
misu-1.0.6.dist-info/RECORD
