Metadata-Version: 2.1
Name: misu
Version: 1.0.6
Summary: Fast quantities
Home-page: https://github.com/cjrh/misu
Author: Caleb Hattingh
Author-email: caleb.hattingh@gmail.com
License: MIT
Keywords: math science engineering physics quantities units
Platform: UNKNOWN
Classifier: Development Status :: 4 - Beta
Classifier: Intended Audience :: Developers
Classifier: Topic :: Software Development :: Build Tools
Classifier: License :: OSI Approved :: MIT License
Classifier: Programming Language :: Python :: 3
Classifier: Programming Language :: Python :: 3.4
Classifier: Programming Language :: Python :: 3.5
Classifier: Programming Language :: Python :: 3.6
Classifier: Programming Language :: Python :: 3.7
Requires-Dist: cython
Requires-Dist: numpy
